ecl3-0.1.0.dist-info/RECORD
ecl3-0.1.0.dist-info/top_level.txt
ecl3-0.1.0.dist-info/METADATA
ecl3-0.1.0.dist-info/WHEEL
ecl3/__init__.py
ecl3/version.py
ecl3/core.cpython-35m-x86_64-linux-gnu.so
ecl3/.libs/libecl3-96f4ea8d.so
ecl3/summary/specification.py
ecl3/summary/__init__.py
