Metadata-Version: 2.1
Name: ecl3
Version: 0.1.0
Summary: ecl3
Home-page: https://github.com/equinor/ecl3
Author: UNKNOWN
Author-email: UNKNOWN
License: LGPL-3.0
Platform: any
Requires-Dist: numpy
